{"status":"OK","result":{"originalLocale":"en","allowViewHistory":false,"creationTimeSeconds":1419449203,"rating":8,"authorHandle":"cheat_founded","modificationTimeSeconds":1419450486,"id":15355,"title":"\u003cp\u003eCheat founded\u003c/p\u003e","locale":"en","content":"\u003cdiv class\u003d\"ttypography\"\u003e\u003cp\u003eHi.\u003c/p\u003e\u003cp\u003eIt sounds like I\u0027ve found 2 cheaters :)\u003c/p\u003e\u003cp\u003elook at these submissions:\u003c/p\u003e\u003cp\u003e\u003ca href\u003d\"/contest/499/submission/9258928\" title\u003d\"Посылка 9258928 от Majid\"\u003e9258928\u003c/a\u003e \u0026amp; \u003ca href\u003d\"/contest/499/submission/9258764\" title\u003d\"Посылка 9258764 от ArEn\"\u003e9258764\u003c/a\u003e\u003c/p\u003e\u003cp\u003eI find them too similar. How about you?\u003c/p\u003e\u003cp\u003eShouldn\u0027t \u003ca class\u003d\"rated-user user-cyan\" href\u003d\"/profile/clashofclans\" title\u003d\"Специалист clashofclans\"\u003eclashofclans\u003c/a\u003e and \u003ca class\u003d\"rated-user user-blue\" href\u003d\"/profile/aren\" title\u003d\"Эксперт aren\"\u003earen\u003c/a\u003e be banned from the contest for cheating?\u003c/p\u003e\u003cp\u003eAs you might have seee it\u0027s said \u003ca href\u003d\"//codeforces.com/blog/entry/15336#comment-202674\"\u003ehere\u003c/a\u003e that \u003ca class\u003d\"rated-user user-cyan\" href\u003d\"/profile/clashofclans\" title\u003d\"Специалист clashofclans\"\u003eclashofclans\u003c/a\u003e has many other accounts too(do you remember \u003ca class\u003d\"rated-user user-green\" href\u003d\"/profile/contest1234\" title\u003d\"Ученик contest1234\"\u003econtest1234\u003c/a\u003e and his/her cheats?).\u003c/p\u003e\u003cp\u003eWhy isn\u0027t he banned from the whole Codeforces?\u003c/p\u003e\u003cp\u003e\u003cstrong\u003eUPD 1\u003c/strong\u003e. for more information about \u003ca class\u003d\"rated-user user-green\" href\u003d\"/profile/contest1234\" title\u003d\"Ученик contest1234\"\u003econtest1234\u003c/a\u003e and his/her cheats you may see \u003ca href\u003d\"//codeforces.com/blog/entry/14126\"\u003ehere\u003c/a\u003e or \u003ca href\u003d\"//codeforces.com/blog/entry/13262\"\u003ehere\u003c/a\u003e\u003c/p\u003e\u003c/div\u003e","tags":["cheat","cheater during contest","nobody reads tags"]}}