{"status":"OK","result":{"originalLocale":"en","allowViewHistory":false,"creationTimeSeconds":1432374579,"rating":80,"authorHandle":"M.Mahdi","modificationTimeSeconds":1432374579,"id":18050,"title":"\u003cp\u003eWhy it\u0027s O(nlogn)?\u003c/p\u003e","locale":"en","content":"\u003cdiv class\u003d\"ttypography\"\u003e\u003cp\u003eHi! \u003cbr /\u003e Did you know \u003cimg align\u003d\"middle\" class\u003d\"tex-formula\" src\u003d\"/predownloaded/b5/d0/b5d03646311d0f205427ad7022ae1f901def6a61.png\" style\u003d\"max-width: 100.0%;max-height: 100.0%;\" /\u003e is \u003cspan class\u003d\"tex-span\"\u003e\u003ci\u003eO\u003c/i\u003e(\u003ci\u003enlogn\u003c/i\u003e)\u003c/span\u003e? (\u003cspan class\u003d\"tex-span\"\u003eω(\u003ci\u003en\u003c/i\u003e)\u003c/span\u003e is the number of distinct prime divisors of \u003cspan class\u003d\"tex-span\"\u003e\u003ci\u003en\u003c/i\u003e\u003c/span\u003e)\u003cbr /\u003e \u003cimg alt\u003d\" \" src\u003d\"/predownloaded/01/e4/01e48703abee1293e4643a5f57c1b031b7ff8276.jpg\" style\u003d\"max-width: 100.0%;max-height: 100.0%;\" /\u003e \u003cbr /\u003e I wonder why! Do you have any mathematical proof for this?\u003c/p\u003e\u003c/div\u003e","tags":["math","number theory","whoreadstaganyway"]}}