{"status":"OK","result":{"originalLocale":"ru","allowViewHistory":true,"creationTimeSeconds":1499265629,"rating":0,"authorHandle":"Tima","modificationTimeSeconds":1501231104,"id":53128,"title":"\u003cp\u003eИюль 2017.\u003c/p\u003e","locale":"ru","content":"\u003cdiv class\u003d\"ttypography\"\u003e\u003cp\u003e\u003cstrong\u003e05.07\u003c/strong\u003e\u003c/p\u003e\u003cp\u003e\u003ca href\u003d\"//codeforces.com/group/GH48wEGAcZ/contest/209562\"\u003eЗадачи C,E\u003c/a\u003e\u003c/p\u003e\u003cp\u003e\u003ca href\u003d\"http://lightoj.com/volume_problemcategory.php?user_id\u003d17601\u0026amp;category\u003dSegment%20Tree/Interval%20Tree\"\u003eLightoj Segment tree\u003c/a\u003e минимум 12 задач. +++\u003c/p\u003e\u003cp\u003e\u003cstrong\u003e17.07\u003c/strong\u003e\u003c/p\u003e\u003cp\u003eLightoj: 1135+, 1080+, 1087+, 1089+. \u003c/p\u003e\u003cp\u003eCodeforces: 817B+. \u003c/p\u003e\u003cp\u003e\u003cstrong\u003e24.07\u003c/strong\u003e\u003c/p\u003e\u003cp\u003eCodeforces : 552C+, 21C+, 585D+, 721C+.\u003c/p\u003e\u003cp\u003e\u003cstrong\u003e27.07\u003c/strong\u003e\u003c/p\u003e\u003cp\u003eCodeforces: 585D+\u003c/p\u003e\u003cp\u003eTimus: 1009+, 1073+, 1017+, 1152+, 1183, 1244, 1495. \u003c/p\u003e\u003cp\u003e\u003cstrong\u003e28.07\u003c/strong\u003e\u003c/p\u003e\u003cp\u003eacmp: 156, 157,299.\u003c/p\u003e\u003cp\u003eЗавтра Codechef Lunchtime в 20:00. И послезавтра Codeforces round. \u003c/p\u003e\u003c/div\u003e","tags":[]}}