{"status":"OK","result":{"originalLocale":"en","allowViewHistory":true,"creationTimeSeconds":1497184291,"rating":0,"authorHandle":"vishaldugyala","modificationTimeSeconds":1497184386,"id":52538,"title":"\u003cp\u003eNeed help with 441B, Valera and fruits\u003c/p\u003e","locale":"en","content":"\u003cdiv class\u003d\"ttypography\"\u003e\u003cp\u003eHi, I am unable to understand what is wrong with my code for \u003ca href\u003d\"//codeforces.com/problemset/problem/441/B\"\u003e441B\u003c/a\u003e,Here is my \u003ca href\u003d\"//codeforces.com/contest/441/submission/27720568\"\u003ecode\u003c/a\u003e. Even though i am able to solve the problem using another approach,I want to understand why this approach is not working. Thanks\u003c/p\u003e\u003c/div\u003e","tags":[]}}