{"status":"OK","result":{"originalLocale":"ru","allowViewHistory":false,"creationTimeSeconds":1409211217,"rating":-10,"authorHandle":"testingcode","modificationTimeSeconds":1409211217,"id":13596,"title":"\u003cp\u003eИндекс матрицы\u003c/p\u003e","locale":"ru","content":"\u003cdiv class\u003d\"ttypography\"\u003e\u003cp\u003eНада матрица NxM\u003c/p\u003e\u003cp\u003eЗадается число \u003cstrong\u003eK\u003c/strong\u003e \u003cem\u003e(K \u0026lt;\u003d N * M)\u003c/em\u003e, нужно вывести координаты \u003cstrong\u003ex\u003c/strong\u003e и \u003cstrong\u003ey\u003c/strong\u003e элемента который является \u003cstrong\u003eK\u003c/strong\u003e-ым по счету. \u003c/p\u003e\u003cp\u003eОтсчет элементов начинается с 1, слева на право, сверху вних.\u003c/p\u003e\u003cp\u003eИ тоже самое наоборот, имея координаты \u003cstrong\u003ex\u003c/strong\u003e и \u003cstrong\u003ey\u003c/strong\u003e на каком месте стоит этот элемент.\u003c/p\u003e\u003cp\u003eКакие идеи? Интересно на ваши решения посмотреть.\u003c/p\u003e\u003c/div\u003e","tags":[]}}