{"status":"OK","result":{"originalLocale":"en","allowViewHistory":true,"creationTimeSeconds":1498761140,"rating":-2,"authorHandle":"gXa","modificationTimeSeconds":1498761171,"id":52989,"title":"\u003cp\u003eLower_Bound And Upper_Bound\u003c/p\u003e","locale":"en","content":"\u003cdiv class\u003d\"ttypography\"\u003e\u003cp\u003eCan lower_bound and upper_bound work with vector of pair\u0026lt;pair\u0026lt;int, int\u0026gt;, int\u0026gt; or nested pairs. I tried doing so but it is showing me error. So, how should we do that?\u003c/p\u003e\u003c/div\u003e","tags":["lower bound","upper_bound"]}}