{"status":"OK","result":{"originalLocale":"ru","allowViewHistory":false,"creationTimeSeconds":1422282360,"rating":2,"authorHandle":"alibi","modificationTimeSeconds":1422287118,"id":16028,"title":"\u003cp\u003eНужна помощь\u003c/p\u003e","locale":"ru","content":"\u003cdiv class\u003d\"ttypography\"\u003e\u003cp\u003eНедавно начал решать задачи на \u003ca href\u003d\"http://cerberus.delosent.com:791/usacogate\"\u003eUSACO training\u003c/a\u003e. И наткнулся на эту \u003ca href\u003d\"http://cerberus.delosent.com:791/usacoprob2?a\u003dxk01C0CLzLO\u0026amp;S\u003dnamenum\"\u003eзадачу\u003c/a\u003e, где нужно использовать строки с какого-то txt-файла. Но я не знаю как! Буду рад если объясните)\u003c/p\u003e\u003ch3\u003e\u003cstrong\u003ePLEASE READ THE TASK BEFORE WRITE A COMMENT!!!\u003c/strong\u003e\u003c/h3\u003e\u003cp\u003e\u003cstrong\u003ePS:\u003c/strong\u003e Пишу я на С++.\u003c/p\u003e\u003c/div\u003e","tags":["usaco","c++"]}}