{"status":"OK","result":{"originalLocale":"en","allowViewHistory":true,"creationTimeSeconds":1482436849,"rating":15,"authorHandle":"d3mon95","modificationTimeSeconds":1482436849,"id":49249,"title":"\u003cp\u003estl equivalents in python\u003c/p\u003e","locale":"en","content":"\u003cdiv class\u003d\"ttypography\"\u003e\u003cp\u003ehey codeforcers, i decided to do something new and decide to learn python so i need some help here. How can i use an equivalent to c++ set stl in python and similarly how can i use an equivalent to c++ map stl , the dict and set() are not sorted, plz help me.It would be great if someone could provide a usful link or something so that i can learn those things.\u003c/p\u003e\u003c/div\u003e","tags":[]}}