{"status":"OK","result":{"originalLocale":"en","allowViewHistory":false,"creationTimeSeconds":1508854337,"rating":5,"authorHandle":"Sahashoo","modificationTimeSeconds":1508854696,"id":55381,"title":"\u003cp\u003eexpecting TLE but get an AC\u003c/p\u003e","locale":"en","content":"\u003cdiv class\u003d\"ttypography\"\u003e\u003cp\u003e\u003ca href\u003d\"//codeforces.com/contest/877/submission/31684311\"\u003eSubmission Link\u003c/a\u003e\u003c/p\u003e\u003cp\u003eHi,\u003c/p\u003e\u003cp\u003eI was thinking about 442-div 2-D problem and I come up with noting except a bad solution.\u003c/p\u003e\u003cp\u003eas I say it was a bad solution because it run from O(n*m*k) thus it should get TLE but I got an AC!?\u003c/p\u003e\u003cp\u003ecan anybody say just why?????\u003c/p\u003e\u003cp\u003esorry for bad Eng.\u003c/p\u003e\u003c/div\u003e","tags":[]}}