{"status":"OK","result":{"originalLocale":"en","allowViewHistory":true,"creationTimeSeconds":1474326843,"rating":0,"authorHandle":"BitHashTech","modificationTimeSeconds":1474326843,"id":47219,"title":"\u003cp\u003eWeek #1 Sheet discussion \u003c/p\u003e","locale":"en","content":"\u003cdiv class\u003d\"ttypography\"\u003e\u003cp\u003eHello,\u003c/p\u003e\u003cp\u003eThis blog is about \u003cstrong\u003e\u0026quot;Week #1 Sheet\u0026quot;\u003c/strong\u003e. \u003c/p\u003e\u003cp\u003eIf you have any discussion about a problem or anything on your mind, you may \u003cstrong\u003ecomment\u003c/strong\u003e here. :)\u003c/p\u003e\u003cp\u003eThere may be an editorial for the sheet which will be posted here too after testing, if needed.\u003c/p\u003e\u003cp\u003eThanks. :)\u003c/p\u003e\u003c/div\u003e","tags":[]}}