{"status":"OK","result":{"originalLocale":"en","allowViewHistory":true,"creationTimeSeconds":1484148005,"rating":1,"authorHandle":"Mr.Awesome","modificationTimeSeconds":1484148005,"id":49715,"title":"\u003cp\u003eHelp with dp problem — Chocolate Bar\u003c/p\u003e","locale":"en","content":"\u003cdiv class\u003d\"ttypography\"\u003e\u003cp\u003eI was checking some solution of this \u003ca href\u003d\"//codeforces.com/contest/598/problem/E\"\u003eproblem\u003c/a\u003e, and I didn\u0027t understand 2 things, let\u0027s look at this \u003ca href\u003d\"//codeforces.com/contest/598/submission/14459801\"\u003esolution\u003c/a\u003e , first why we loop over k j(0..k), and second why k replaced by j and k-j in each call?\u003c/p\u003e\u003c/div\u003e","tags":["dp"]}}