{"status":"OK","result":{"originalLocale":"en","allowViewHistory":false,"creationTimeSeconds":1400228810,"rating":9,"authorHandle":"KartalKaan","modificationTimeSeconds":1400228810,"id":12320,"title":"\u003cp\u003eQuestion on Pointer Arithmetic\u003c/p\u003e","locale":"en","content":"\u003cdiv class\u003d\"ttypography\"\u003e\u003cp\u003eHello everyone! I have two codes, they print different things but I don\u0027t know why. The first one is :\u003c/p\u003e \u003cpre\u003e\u003ccode\u003e#include \u0026lt;stdio.h\u0026gt;\nint main()\n{\n   int p[6]\u003d{1,2,3,4,5,6};\n   int *q\u003d(int *)(\u0026amp;p+1);\n   printf(\u0026quot;%ld\\n\u0026quot;,q-p);\n   return 0;\n}\n\u003c/code\u003e\u003c/pre\u003e\u003cp\u003eAnd the second one :\u003c/p\u003e \u003cpre\u003e\u003ccode\u003e#include \u0026lt;stdio.h\u0026gt;\nint main()\n{\n   int p[6]\u003d{1,2,3,4,5,6};\n   int *q\u003d(int *)(p+1);\n   printf(\u0026quot;%ld\\n\u0026quot;,q-p);\n   return 0;\n}\n\u003c/code\u003e\u003c/pre\u003e\u003cp\u003eFirst code prints 6, whereas the second one prints 1. The only difference is that the first code has an ampersand before \u0026quot;p+1\u0026quot;. Do you know the reason? Thanks.\u003c/p\u003e\u003c/div\u003e","tags":["pointer","arithmetic","c language"]}}