{"status":"OK","result":{"originalLocale":"en","allowViewHistory":false,"creationTimeSeconds":1429081251,"rating":14,"authorHandle":"NeverSayNever","modificationTimeSeconds":1429081251,"id":17410,"title":"\u003cp\u003eHow to keep myself consistent at solving Div2 D or Div1 B ?\u003c/p\u003e","locale":"en","content":"\u003cdiv class\u003d\"ttypography\"\u003e\u003cp\u003eHello cool coders out here ..\u003c/p\u003e\u003cp\u003eRound Div1 299 was the first round when i am able to solve problem B during the contest itself and i feel very motivated after this. I want to be consistent at solving B during contest like i am on solving A. So, Suggest me something to keep myself consistent. I am eagerly waiting to read your valuable comments :). I was not much focussed during the last contest but still i solved two problems (it was really an amazing experience for me) or may be problem A and B were easy. \u003c/p\u003e\u003c/div\u003e","tags":[]}}