{"status":"OK","result":{"originalLocale":"en","allowViewHistory":false,"creationTimeSeconds":1399379963,"rating":0,"authorHandle":"the_silliest","modificationTimeSeconds":1399379986,"id":12220,"title":"\u003cp\u003eStudied C++ for Four Months\u003c/p\u003e","locale":"en","content":"\u003cdiv class\u003d\"ttypography\"\u003e\u003cp\u003eI studied cpp for four months. I\u0027ve been a speacialist! But I\u0027ve not solved a C in codeforces contest(Div2). I must stedied harder and harder. My goal is to become an expert.\u003c/p\u003e\u003c/div\u003e","tags":[]}}