{"status":"OK","result":{"originalLocale":"en","allowViewHistory":false,"creationTimeSeconds":1417607777,"rating":-29,"authorHandle":"saifislam804","modificationTimeSeconds":1417607912,"id":14980,"title":"\u003cp\u003eSolution of Watermelon( In 2 ways)\u003c/p\u003e","locale":"en","content":"\u003cdiv class\u003d\"ttypography\"\u003e\u003cp\u003e\u0026lt;\u0026gt;\u003c/p\u003e\u003cp\u003eint main() {  int s;  cin \u0026gt;\u0026gt; s;  if(s % 2 \u003d\u003d 0 \u0026amp;\u0026amp; s \u0026gt; 2)  cout \u0026lt;\u0026lt; \u0026quot;YES\u0026quot; \u0026lt;\u0026lt; endl;  else  cout \u0026lt;\u0026lt; \u0026quot;NO\u0026quot; \u0026lt;\u0026lt; endl;  return 0; }\u003c/p\u003e\u003cp\u003e\u0026lt;\u0026gt;(\u0026quot;THE DETAIL ONE\u0026quot;)\u003c/p\u003e\u003ch1\u003einclude\u003c/h1\u003e\u003ch1\u003einclude\u003c/h1\u003e\u003ch1\u003einclude\u003c/h1\u003e\u003cp\u003eusing namespace std; int main(){  srand(time(0));  int x,y,z\u003d0; cout\u0026lt;\u0026lt;\u0026quot;What is the weight of the watermelon \u0026quot;\u0026lt;\u0026lt;endl; cin\u0026gt;\u0026gt;x; y\u003d1+(rand()%x); cout\u0026lt;\u0026lt;y\u0026lt;\u0026lt;endl; z\u003dx-y; cout\u0026lt;\u0026lt;z\u0026lt;\u0026lt;endl; if(y%2\u003d\u003d0\u0026amp;\u0026amp;z%2\u003d\u003d0)  cout\u0026lt;\u0026lt;\u0026quot;Yes\u0026quot;\u0026lt;\u0026lt;endl;  else  cout\u0026lt;\u0026lt;\u0026quot;No\u0026quot;\u0026lt;\u0026lt;endl;  return 0; }\u003c/p\u003e\u003cp\u003eThis code is also correct....But it will not accpet...Beacuse here i used rand() function\u003c/p\u003e\u003cp\u003eIslam,Md.Saiful\u003c/p\u003e\u003c/div\u003e","tags":["english"]}}